rov_db_access/__init__.py
rov_db_access/authentication/__init__.py
rov_db_access/authentication/models.py
rov_db_access/authentication/worker.py
rov_db_access/config/__init__.py
rov_db_access/config/db_utils.py
rov_db_access/config/settings.py
rov_db_access/element84/__init__.py
rov_db_access/element84/element84_client.py
rov_db_access/element84/item.py
rov_db_access/element84/query.py
rov_db_access/element84/tasks.py
rov_db_access/element84/usage.py
rov_db_access/element84/utils.py
rov_db_access/geodata/__init__.py
rov_db_access/geodata/models.py
rov_db_access/gis/__init__.py
rov_db_access/gis/geo_operations.py
rov_db_access/gis/models.py
rov_db_access/gis/test.py
rov_db_access/gis/utils.py
rov_db_access/gis/worker.py
rov_db_access/ine/__init__.py
rov_db_access/ine/models.py
rov_db_access/ine/worker.py
rov_db_access/label_studio/__init__.py
rov_db_access/label_studio/models.py
rov_db_access/label_studio/worker.py
rov_db_access/landing/__init__.py
rov_db_access/landing/models.py
rov_db_access/landing/worker.py
rov_db_access/logging/__init__.py
rov_db_access/logging/utils.py
rov_db_access/risks/__init__.py
rov_db_access/risks/models.py
rov_db_access/risks/worker.py
rov_db_access/sentinel/__init__.py
rov_db_access/sentinel/models.py
rov_db_access/sentinel/worker.py
rov_db_access/utils/__init__.py
rov_db_access/utils/geoserver_utils.py
rov_db_access/utils/s3_utils.py
rov_db_access/utils/utils.py
rov_db_access-1.5.0.dist-info/METADATA
rov_db_access-1.5.0.dist-info/WHEEL
rov_db_access-1.5.0.dist-info/RECORD
