Metadata-Version: 2.1
Name: rov-db-access
Version: 1.5.0
Summary: 
Author: Pablo Cano
Author-email: pablo.cano@rovisen.com
Requires-Python: >=3.9,<4.0
Classifier: Programming Language :: Python :: 3
Classifier: Programming Language :: Python :: 3.9
Classifier: Programming Language :: Python :: 3.10
Classifier: Programming Language :: Python :: 3.11
Classifier: Programming Language :: Python :: 3.12
Requires-Dist: alembic (>=1.13.1,<2.0.0)
Requires-Dist: aws-lambda-powertools (>=2.42.0,<3.0.0)
Requires-Dist: boto3 (>=1.34.99,<2.0.0)
Requires-Dist: geoalchemy2 (>=0.14.2,<0.15.0)
Requires-Dist: geojson (>=3.1.0,<4.0.0)
Requires-Dist: geopandas (>=1.0.1,<2.0.0)
Requires-Dist: pillow (>=10.3.0,<11.0.0)
Requires-Dist: psycopg2-binary (>=2.9.9,<3.0.0)
Requires-Dist: pydantic-settings (>=2.2.1,<3.0.0)
Requires-Dist: pyproj (>=3.6.1,<4.0.0)
Requires-Dist: pystac (>=1.10.1,<2.0.0)
Requires-Dist: pystac-client (>=0.8.2,<0.9.0)
Requires-Dist: rasterio[s3] (>=1.3.10,<2.0.0)
Requires-Dist: rov-sent-api (>=0.1.24,<0.2.0)
Requires-Dist: shapely (>=2.0.4,<3.0.0)
Requires-Dist: sqlalchemy (>=2.0.23,<3.0.0)
